rait_connector/__init__.py
rait_connector/auth.py
rait_connector/client.py
rait_connector/config.py
rait_connector/constants.py
rait_connector/encryption.py
rait_connector/exceptions.py
rait_connector/http.py
rait_connector/models.py
rait_connector/evaluators/__init__.py
rait_connector/evaluators/base.py
rait_connector/evaluators/orchestrator.py
rait_connector/evaluators/registry.py
rait_connector-0.1.0.dist-info/METADATA
rait_connector-0.1.0.dist-info/WHEEL
rait_connector-0.1.0.dist-info/licenses/LICENSE
rait_connector-0.1.0.dist-info/RECORD
