Metadata-Version: 2.4
Name: rait-connector
Version: 0.1.0
Summary: Python library for evaluating LLM outputs across multiple ethical dimensions and performance metrics using Azure AI Evaluation services.
License-File: LICENSE
Classifier: Development Status :: 3 - Alpha
Classifier: Programming Language :: Python :: 3.12
Requires-Python: >=3.12
Requires-Dist: azure-ai-evaluation>=1.12.0
Requires-Dist: cryptography>=46.0.3
Requires-Dist: pydantic-settings>=2.12.0
